[
  {
    "front": "What is the timeline and majority required to approve a National Emergency (Article 352)?",
    "back": "Within 1 month by a Special Majority in both Houses."
  },
  {
    "front": "What are the three grounds for declaring a National Emergency?",
    "back": "War, External Aggression, and Armed Rebellion."
  },
  {
    "front": "Which amendment replaced 'Internal Disturbance' with 'Armed Rebellion' for National Emergency?",
    "back": "44th Amendment Act (1978)."
  },
  {
    "front": "What is the timeline and majority required to approve President's Rule (Article 356)?",
    "back": "Within 2 months by a Simple Majority in both Houses."
  },
  {
    "front": "What is the timeline and majority required to approve Financial Emergency (Article 360)?",
    "back": "Within 2 months by a Simple Majority in both Houses."
  },
  {
    "front": "Which two fundamental rights can NEVER be suspended during any emergency?",
    "back": "Articles 20 and 21."
  },
  {
    "front": "Which article provides for the automatic suspension of Article 19 during war or external aggression?",
    "back": "Article 358."
  },
  {
    "front": "Which article empowers the President to suspend the enforcement of other Fundamental Rights (except 20 & 21) during emergencies?",
    "back": "Article 359."
  },
  {
    "front": "What is the maximum duration President's Rule can be extended (with parliamentary approvals every 6 months)?",
    "back": "3 years."
  },
  {
    "front": "Which amendment is known as the 'Mini-Constitution'?",
    "back": "42nd Amendment Act (1976)."
  },
  {
    "front": "Which amendment converted the Right to Property into a legal right under Article 300A?",
    "back": "44th Amendment Act (1978)."
  },
  {
    "front": "Which amendment introduced the Anti-Defection Law (Tenth Schedule)?",
    "back": "52nd Amendment Act (1985)."
  },
  {
    "front": "Which amendment lowered the voting age from 21 to 18 years?",
    "back": "61st Amendment Act (1988)."
  },
  {
    "front": "Which amendment gave constitutional status to Panchayati Raj Institutions (Part IX)?",
    "back": "73rd Amendment Act (1992)."
  },
  {
    "front": "Which amendment gave constitutional status to Municipalities (Part IX-A)?",
    "back": "74th Amendment Act (1992)."
  },
  {
    "front": "Which amendment made elementary education a Fundamental Right (Article 21A)?",
    "back": "86th Amendment Act (2002)."
  },
  {
    "front": "Which amendment capped the size of the Council of Ministers at 15% of the Lok Sabha / State Assembly strength?",
    "back": "91st Amendment Act (2003)."
  },
  {
    "front": "Which amendment introduced the Goods and Services Tax (GST) and the GST Council (Article 279A)?",
    "back": "101st Amendment Act (2016)."
  },
  {
    "front": "Which amendment introduced the 10% EWS reservation in education and employment?",
    "back": "103rd Amendment Act (2019)."
  },
  {
    "front": "In which landmark case was the Basic Structure Doctrine propounded by the Supreme Court?",
    "back": "Kesavananda Bharati case (1973)."
  }
]
